README.md
pyproject.toml
nztm/ConvertToWGS84Test.py
nztm/__init__.py
nztm/lib.py
nztm/tuples.py
nztm/util.py
nztm.egg-info/PKG-INFO
nztm.egg-info/SOURCES.txt
nztm.egg-info/dependency_links.txt
nztm.egg-info/top_level.txt